{"nodes": [{"id": "c_users_pujar_documents_tripsense_wad_app_api_trips_from_discover_route_ts", "label": "route.ts", "file_type": "code", "source_file": "C:\\Users\\pujar\\Documents\\TripSense(WAD)\\app\\api\\trips\\from-discover\\route.ts", "source_location": "L1"}, {"id": "route_todaydatestring", "label": "todayDateString()", "file_type": "code", "source_file": "C:\\Users\\pujar\\Documents\\TripSense(WAD)\\app\\api\\trips\\from-discover\\route.ts", "source_location": "L94"}, {"id": "route_adddays", "label": "addDays()", "file_type": "code", "source_file": "C:\\Users\\pujar\\Documents\\TripSense(WAD)\\app\\api\\trips\\from-discover\\route.ts", "source_location": "L98"}, {"id": "route_isvaliddatestring", "label": "isValidDateString()", "file_type": "code", "source_file": "C:\\Users\\pujar\\Documents\\TripSense(WAD)\\app\\api\\trips\\from-discover\\route.ts", "source_location": "L104"}, {"id": "route_safestringarray", "label": "safeStringArray()", "file_type": "code", "source_file": "C:\\Users\\pujar\\Documents\\TripSense(WAD)\\app\\api\\trips\\from-discover\\route.ts", "source_location": "L108"}, {"id": "route_parsestatusfrommessage", "label": "parseStatusFromMessage()", "file_type": "code", "source_file": "C:\\Users\\pujar\\Documents\\TripSense(WAD)\\app\\api\\trips\\from-discover\\route.ts", "source_location": "L113"}, {"id": "route_istransientailoaderror", "label": "isTransientAiLoadError()", "file_type": "code", "source_file": "C:\\Users\\pujar\\Documents\\TripSense(WAD)\\app\\api\\trips\\from-discover\\route.ts", "source_location": "L118"}, {"id": "route_parsedurationdays", "label": "parseDurationDays()", "file_type": "code", "source_file": "C:\\Users\\pujar\\Documents\\TripSense(WAD)\\app\\api\\trips\\from-discover\\route.ts", "source_location": "L134"}, {"id": "route_inferbudgettier", "label": "inferBudgetTier()", "file_type": "code", "source_file": "C:\\Users\\pujar\\Documents\\TripSense(WAD)\\app\\api\\trips\\from-discover\\route.ts", "source_location": "L140"}, {"id": "route_infervibes", "label": "inferVibes()", "file_type": "code", "source_file": "C:\\Users\\pujar\\Documents\\TripSense(WAD)\\app\\api\\trips\\from-discover\\route.ts", "source_location": "L155"}, {"id": "route_normalizesentence", "label": "normalizeSentence()", "file_type": "code", "source_file": "C:\\Users\\pujar\\Documents\\TripSense(WAD)\\app\\api\\trips\\from-discover\\route.ts", "source_location": "L169"}, {"id": "route_splitdescriptionintosegments", "label": "splitDescriptionIntoSegments()", "file_type": "code", "source_file": "C:\\Users\\pujar\\Documents\\TripSense(WAD)\\app\\api\\trips\\from-discover\\route.ts", "source_location": "L175"}, {"id": "route_inferactivitytype", "label": "inferActivityType()", "file_type": "code", "source_file": "C:\\Users\\pujar\\Documents\\TripSense(WAD)\\app\\api\\trips\\from-discover\\route.ts", "source_location": "L197"}, {"id": "route_extractproperphrases", "label": "extractProperPhrases()", "file_type": "code", "source_file": "C:\\Users\\pujar\\Documents\\TripSense(WAD)\\app\\api\\trips\\from-discover\\route.ts", "source_location": "L219"}, {"id": "route_sentencetoactivitytitle", "label": "sentenceToActivityTitle()", "file_type": "code", "source_file": "C:\\Users\\pujar\\Documents\\TripSense(WAD)\\app\\api\\trips\\from-discover\\route.ts", "source_location": "L233"}, {"id": "route_buildseededfallbackimage", "label": "buildSeededFallbackImage()", "file_type": "code", "source_file": "C:\\Users\\pujar\\Documents\\TripSense(WAD)\\app\\api\\trips\\from-discover\\route.ts", "source_location": "L263"}, {"id": "route_inferbridgeactivitytitle", "label": "inferBridgeActivityTitle()", "file_type": "code", "source_file": "C:\\Users\\pujar\\Documents\\TripSense(WAD)\\app\\api\\trips\\from-discover\\route.ts", "source_location": "L269"}, {"id": "route_buildfallbackactivitiesforday", "label": "buildFallbackActivitiesForDay()", "file_type": "code", "source_file": "C:\\Users\\pujar\\Documents\\TripSense(WAD)\\app\\api\\trips\\from-discover\\route.ts", "source_location": "L288"}, {"id": "route_mergeactivitieswithfallback", "label": "mergeActivitiesWithFallback()", "file_type": "code", "source_file": "C:\\Users\\pujar\\Documents\\TripSense(WAD)\\app\\api\\trips\\from-discover\\route.ts", "source_location": "L405"}, {"id": "route_sanitizegenerateddiscoveritinerary", "label": "sanitizeGeneratedDiscoverItinerary()", "file_type": "code", "source_file": "C:\\Users\\pujar\\Documents\\TripSense(WAD)\\app\\api\\trips\\from-discover\\route.ts", "source_location": "L431"}, {"id": "route_builddiscoverexpansionprompt", "label": "buildDiscoverExpansionPrompt()", "file_type": "code", "source_file": "C:\\Users\\pujar\\Documents\\TripSense(WAD)\\app\\api\\trips\\from-discover\\route.ts", "source_location": "L514"}, {"id": "route_resolveuserid", "label": "resolveUserId()", "file_type": "code", "source_file": "C:\\Users\\pujar\\Documents\\TripSense(WAD)\\app\\api\\trips\\from-discover\\route.ts", "source_location": "L579"}, {"id": "route_buildestimateprompt", "label": "buildEstimatePrompt()", "file_type": "code", "source_file": "C:\\Users\\pujar\\Documents\\TripSense(WAD)\\app\\api\\trips\\from-discover\\route.ts", "source_location": "L603"}, {"id": "route_post", "label": "POST()", "file_type": "code", "source_file": "C:\\Users\\pujar\\Documents\\TripSense(WAD)\\app\\api\\trips\\from-discover\\route.ts", "source_location": "L650"}], "edges": [{"source": "c_users_pujar_documents_tripsense_wad_app_api_trips_from_discover_route_ts", "target": "server", "relation": "imports_from", "confidence": "EXTRACTED", "source_file": "C:\\Users\\pujar\\Documents\\TripSense(WAD)\\app\\api\\trips\\from-discover\\route.ts", "source_location": "L1", "weight": 1.0}, {"source": "c_users_pujar_documents_tripsense_wad_app_api_trips_from_discover_route_ts", "target": "drizzle_orm", "relation": "imports_from", "confidence": "EXTRACTED", "source_file": "C:\\Users\\pujar\\Documents\\TripSense(WAD)\\app\\api\\trips\\from-discover\\route.ts", "source_location": "L2", "weight": 1.0}, {"source": "c_users_pujar_documents_tripsense_wad_app_api_trips_from_discover_route_ts", "target": "db", "relation": "imports_from", "confidence": "EXTRACTED", "source_file": "C:\\Users\\pujar\\Documents\\TripSense(WAD)\\app\\api\\trips\\from-discover\\route.ts", "source_location": "L3", "weight": 1.0}, {"source": "c_users_pujar_documents_tripsense_wad_app_api_trips_from_discover_route_ts", "target": "schema", "relation": "imports_from", "confidence": "EXTRACTED", "source_file": "C:\\Users\\pujar\\Documents\\TripSense(WAD)\\app\\api\\trips\\from-discover\\route.ts", "source_location": "L4", "weight": 1.0}, {"source": "c_users_pujar_documents_tripsense_wad_app_api_trips_from_discover_route_ts", "target": "discovertrips", "relation": "imports_from", "confidence": "EXTRACTED", "source_file": "C:\\Users\\pujar\\Documents\\TripSense(WAD)\\app\\api\\trips\\from-discover\\route.ts", "source_location": "L5", "weight": 1.0}, {"source": "c_users_pujar_documents_tripsense_wad_app_api_trips_from_discover_route_ts", "target": "gemini", "relation": "imports_from", "confidence": "EXTRACTED", "source_file": "C:\\Users\\pujar\\Documents\\TripSense(WAD)\\app\\api\\trips\\from-discover\\route.ts", "source_location": "L6", "weight": 1.0}, {"source": "c_users_pujar_documents_tripsense_wad_app_api_trips_from_discover_route_ts", "target": "location_image", "relation": "imports_from", "confidence": "EXTRACTED", "source_file": "C:\\Users\\pujar\\Documents\\TripSense(WAD)\\app\\api\\trips\\from-discover\\route.ts", "source_location": "L7", "weight": 1.0}, {"source": "c_users_pujar_documents_tripsense_wad_app_api_trips_from_discover_route_ts", "target": "trip_pricing", "relation": "imports_from", "confidence": "EXTRACTED", "source_file": "C:\\Users\\pujar\\Documents\\TripSense(WAD)\\app\\api\\trips\\from-discover\\route.ts", "source_location": "L8", "weight": 1.0}, {"source": "c_users_pujar_documents_tripsense_wad_app_api_trips_from_discover_route_ts", "target": "route_todaydatestring", "relation": "contains", "confidence": "EXTRACTED", "source_file": "C:\\Users\\pujar\\Documents\\TripSense(WAD)\\app\\api\\trips\\from-discover\\route.ts", "source_location": "L94", "weight": 1.0}, {"source": "c_users_pujar_documents_tripsense_wad_app_api_trips_from_discover_route_ts", "target": "route_adddays", "relation": "contains", "confidence": "EXTRACTED", "source_file": "C:\\Users\\pujar\\Documents\\TripSense(WAD)\\app\\api\\trips\\from-discover\\route.ts", "source_location": "L98", "weight": 1.0}, {"source": "c_users_pujar_documents_tripsense_wad_app_api_trips_from_discover_route_ts", "target": "route_isvaliddatestring", "relation": "contains", "confidence": "EXTRACTED", "source_file": "C:\\Users\\pujar\\Documents\\TripSense(WAD)\\app\\api\\trips\\from-discover\\route.ts", "source_location": "L104", "weight": 1.0}, {"source": "c_users_pujar_documents_tripsense_wad_app_api_trips_from_discover_route_ts", "target": "route_safestringarray", "relation": "contains", "confidence": "EXTRACTED", "source_file": "C:\\Users\\pujar\\Documents\\TripSense(WAD)\\app\\api\\trips\\from-discover\\route.ts", "source_location": "L108", "weight": 1.0}, {"source": "c_users_pujar_documents_tripsense_wad_app_api_trips_from_discover_route_ts", "target": "route_parsestatusfrommessage", "relation": "contains", "confidence": "EXTRACTED", "source_file": "C:\\Users\\pujar\\Documents\\TripSense(WAD)\\app\\api\\trips\\from-discover\\route.ts", "source_location": "L113", "weight": 1.0}, {"source": "c_users_pujar_documents_tripsense_wad_app_api_trips_from_discover_route_ts", "target": "route_istransientailoaderror", "relation": "contains", "confidence": "EXTRACTED", "source_file": "C:\\Users\\pujar\\Documents\\TripSense(WAD)\\app\\api\\trips\\from-discover\\route.ts", "source_location": "L118", "weight": 1.0}, {"source": "c_users_pujar_documents_tripsense_wad_app_api_trips_from_discover_route_ts", "target": "route_parsedurationdays", "relation": "contains", "confidence": "EXTRACTED", "source_file": "C:\\Users\\pujar\\Documents\\TripSense(WAD)\\app\\api\\trips\\from-discover\\route.ts", "source_location": "L134", "weight": 1.0}, {"source": "c_users_pujar_documents_tripsense_wad_app_api_trips_from_discover_route_ts", "target": "route_inferbudgettier", "relation": "contains", "confidence": "EXTRACTED", "source_file": "C:\\Users\\pujar\\Documents\\TripSense(WAD)\\app\\api\\trips\\from-discover\\route.ts", "source_location": "L140", "weight": 1.0}, {"source": "c_users_pujar_documents_tripsense_wad_app_api_trips_from_discover_route_ts", "target": "route_infervibes", "relation": "contains", "confidence": "EXTRACTED", "source_file": "C:\\Users\\pujar\\Documents\\TripSense(WAD)\\app\\api\\trips\\from-discover\\route.ts", "source_location": "L155", "weight": 1.0}, {"source": "c_users_pujar_documents_tripsense_wad_app_api_trips_from_discover_route_ts", "target": "route_normalizesentence", "relation": "contains", "confidence": "EXTRACTED", "source_file": "C:\\Users\\pujar\\Documents\\TripSense(WAD)\\app\\api\\trips\\from-discover\\route.ts", "source_location": "L169", "weight": 1.0}, {"source": "c_users_pujar_documents_tripsense_wad_app_api_trips_from_discover_route_ts", "target": "route_splitdescriptionintosegments", "relation": "contains", "confidence": "EXTRACTED", "source_file": "C:\\Users\\pujar\\Documents\\TripSense(WAD)\\app\\api\\trips\\from-discover\\route.ts", "source_location": "L175", "weight": 1.0}, {"source": "c_users_pujar_documents_tripsense_wad_app_api_trips_from_discover_route_ts", "target": "route_inferactivitytype", "relation": "contains", "confidence": "EXTRACTED", "source_file": "C:\\Users\\pujar\\Documents\\TripSense(WAD)\\app\\api\\trips\\from-discover\\route.ts", "source_location": "L197", "weight": 1.0}, {"source": "c_users_pujar_documents_tripsense_wad_app_api_trips_from_discover_route_ts", "target": "route_extractproperphrases", "relation": "contains", "confidence": "EXTRACTED", "source_file": "C:\\Users\\pujar\\Documents\\TripSense(WAD)\\app\\api\\trips\\from-discover\\route.ts", "source_location": "L219", "weight": 1.0}, {"source": "c_users_pujar_documents_tripsense_wad_app_api_trips_from_discover_route_ts", "target": "route_sentencetoactivitytitle", "relation": "contains", "confidence": "EXTRACTED", "source_file": "C:\\Users\\pujar\\Documents\\TripSense(WAD)\\app\\api\\trips\\from-discover\\route.ts", "source_location": "L233", "weight": 1.0}, {"source": "c_users_pujar_documents_tripsense_wad_app_api_trips_from_discover_route_ts", "target": "route_buildseededfallbackimage", "relation": "contains", "confidence": "EXTRACTED", "source_file": "C:\\Users\\pujar\\Documents\\TripSense(WAD)\\app\\api\\trips\\from-discover\\route.ts", "source_location": "L263", "weight": 1.0}, {"source": "c_users_pujar_documents_tripsense_wad_app_api_trips_from_discover_route_ts", "target": "route_inferbridgeactivitytitle", "relation": "contains", "confidence": "EXTRACTED", "source_file": "C:\\Users\\pujar\\Documents\\TripSense(WAD)\\app\\api\\trips\\from-discover\\route.ts", "source_location": "L269", "weight": 1.0}, {"source": "c_users_pujar_documents_tripsense_wad_app_api_trips_from_discover_route_ts", "target": "route_buildfallbackactivitiesforday", "relation": "contains", "confidence": "EXTRACTED", "source_file": "C:\\Users\\pujar\\Documents\\TripSense(WAD)\\app\\api\\trips\\from-discover\\route.ts", "source_location": "L288", "weight": 1.0}, {"source": "c_users_pujar_documents_tripsense_wad_app_api_trips_from_discover_route_ts", "target": "route_mergeactivitieswithfallback", "relation": "contains", "confidence": "EXTRACTED", "source_file": "C:\\Users\\pujar\\Documents\\TripSense(WAD)\\app\\api\\trips\\from-discover\\route.ts", "source_location": "L405", "weight": 1.0}, {"source": "c_users_pujar_documents_tripsense_wad_app_api_trips_from_discover_route_ts", "target": "route_sanitizegenerateddiscoveritinerary", "relation": "contains", "confidence": "EXTRACTED", "source_file": "C:\\Users\\pujar\\Documents\\TripSense(WAD)\\app\\api\\trips\\from-discover\\route.ts", "source_location": "L431", "weight": 1.0}, {"source": "c_users_pujar_documents_tripsense_wad_app_api_trips_from_discover_route_ts", "target": "route_builddiscoverexpansionprompt", "relation": "contains", "confidence": "EXTRACTED", "source_file": "C:\\Users\\pujar\\Documents\\TripSense(WAD)\\app\\api\\trips\\from-discover\\route.ts", "source_location": "L514", "weight": 1.0}, {"source": "c_users_pujar_documents_tripsense_wad_app_api_trips_from_discover_route_ts", "target": "route_resolveuserid", "relation": "contains", "confidence": "EXTRACTED", "source_file": "C:\\Users\\pujar\\Documents\\TripSense(WAD)\\app\\api\\trips\\from-discover\\route.ts", "source_location": "L579", "weight": 1.0}, {"source": "c_users_pujar_documents_tripsense_wad_app_api_trips_from_discover_route_ts", "target": "route_buildestimateprompt", "relation": "contains", "confidence": "EXTRACTED", "source_file": "C:\\Users\\pujar\\Documents\\TripSense(WAD)\\app\\api\\trips\\from-discover\\route.ts", "source_location": "L603", "weight": 1.0}, {"source": "c_users_pujar_documents_tripsense_wad_app_api_trips_from_discover_route_ts", "target": "route_post", "relation": "contains", "confidence": "EXTRACTED", "source_file": "C:\\Users\\pujar\\Documents\\TripSense(WAD)\\app\\api\\trips\\from-discover\\route.ts", "source_location": "L650", "weight": 1.0}, {"source": "route_istransientailoaderror", "target": "route_parsestatusfrommessage", "relation": "calls", "confidence": "EXTRACTED", "source_file": "C:\\Users\\pujar\\Documents\\TripSense(WAD)\\app\\api\\trips\\from-discover\\route.ts", "source_location": "L120", "weight": 1.0}, {"source": "route_infervibes", "target": "route_safestringarray", "relation": "calls", "confidence": "EXTRACTED", "source_file": "C:\\Users\\pujar\\Documents\\TripSense(WAD)\\app\\api\\trips\\from-discover\\route.ts", "source_location": "L156", "weight": 1.0}, {"source": "route_splitdescriptionintosegments", "target": "route_normalizesentence", "relation": "calls", "confidence": "EXTRACTED", "source_file": "C:\\Users\\pujar\\Documents\\TripSense(WAD)\\app\\api\\trips\\from-discover\\route.ts", "source_location": "L176", "weight": 1.0}, {"source": "route_sentencetoactivitytitle", "target": "route_extractproperphrases", "relation": "calls", "confidence": "EXTRACTED", "source_file": "C:\\Users\\pujar\\Documents\\TripSense(WAD)\\app\\api\\trips\\from-discover\\route.ts", "source_location": "L238", "weight": 1.0}, {"source": "route_inferbridgeactivitytitle", "target": "route_extractproperphrases", "relation": "calls", "confidence": "EXTRACTED", "source_file": "C:\\Users\\pujar\\Documents\\TripSense(WAD)\\app\\api\\trips\\from-discover\\route.ts", "source_location": "L270", "weight": 1.0}, {"source": "route_buildfallbackactivitiesforday", "target": "route_normalizesentence", "relation": "calls", "confidence": "EXTRACTED", "source_file": "C:\\Users\\pujar\\Documents\\TripSense(WAD)\\app\\api\\trips\\from-discover\\route.ts", "source_location": "L295", "weight": 1.0}, {"source": "route_buildfallbackactivitiesforday", "target": "route_inferbridgeactivitytitle", "relation": "calls", "confidence": "EXTRACTED", "source_file": "C:\\Users\\pujar\\Documents\\TripSense(WAD)\\app\\api\\trips\\from-discover\\route.ts", "source_location": "L319", "weight": 1.0}, {"source": "route_post", "target": "route_isvaliddatestring", "relation": "calls", "confidence": "EXTRACTED", "source_file": "C:\\Users\\pujar\\Documents\\TripSense(WAD)\\app\\api\\trips\\from-discover\\route.ts", "source_location": "L664", "weight": 1.0}, {"source": "route_post", "target": "route_todaydatestring", "relation": "calls", "confidence": "EXTRACTED", "source_file": "C:\\Users\\pujar\\Documents\\TripSense(WAD)\\app\\api\\trips\\from-discover\\route.ts", "source_location": "L666", "weight": 1.0}, {"source": "route_post", "target": "route_parsedurationdays", "relation": "calls", "confidence": "EXTRACTED", "source_file": "C:\\Users\\pujar\\Documents\\TripSense(WAD)\\app\\api\\trips\\from-discover\\route.ts", "source_location": "L667", "weight": 1.0}, {"source": "route_post", "target": "route_adddays", "relation": "calls", "confidence": "EXTRACTED", "source_file": "C:\\Users\\pujar\\Documents\\TripSense(WAD)\\app\\api\\trips\\from-discover\\route.ts", "source_location": "L668", "weight": 1.0}, {"source": "route_post", "target": "route_inferbudgettier", "relation": "calls", "confidence": "EXTRACTED", "source_file": "C:\\Users\\pujar\\Documents\\TripSense(WAD)\\app\\api\\trips\\from-discover\\route.ts", "source_location": "L669", "weight": 1.0}, {"source": "route_post", "target": "route_infervibes", "relation": "calls", "confidence": "EXTRACTED", "source_file": "C:\\Users\\pujar\\Documents\\TripSense(WAD)\\app\\api\\trips\\from-discover\\route.ts", "source_location": "L671", "weight": 1.0}, {"source": "route_post", "target": "route_resolveuserid", "relation": "calls", "confidence": "EXTRACTED", "source_file": "C:\\Users\\pujar\\Documents\\TripSense(WAD)\\app\\api\\trips\\from-discover\\route.ts", "source_location": "L673", "weight": 1.0}, {"source": "route_post", "target": "route_builddiscoverexpansionprompt", "relation": "calls", "confidence": "EXTRACTED", "source_file": "C:\\Users\\pujar\\Documents\\TripSense(WAD)\\app\\api\\trips\\from-discover\\route.ts", "source_location": "L678", "weight": 1.0}, {"source": "route_post", "target": "route_istransientailoaderror", "relation": "calls", "confidence": "EXTRACTED", "source_file": "C:\\Users\\pujar\\Documents\\TripSense(WAD)\\app\\api\\trips\\from-discover\\route.ts", "source_location": "L696", "weight": 1.0}, {"source": "route_post", "target": "route_sanitizegenerateddiscoveritinerary", "relation": "calls", "confidence": "EXTRACTED", "source_file": "C:\\Users\\pujar\\Documents\\TripSense(WAD)\\app\\api\\trips\\from-discover\\route.ts", "source_location": "L701", "weight": 1.0}, {"source": "route_post", "target": "route_buildestimateprompt", "relation": "calls", "confidence": "EXTRACTED", "source_file": "C:\\Users\\pujar\\Documents\\TripSense(WAD)\\app\\api\\trips\\from-discover\\route.ts", "source_location": "L718", "weight": 1.0}], "raw_calls": [{"caller_nid": "route_todaydatestring", "callee": "split", "source_file": "C:\\Users\\pujar\\Documents\\TripSense(WAD)\\app\\api\\trips\\from-discover\\route.ts", "source_location": "L95"}, {"caller_nid": "route_todaydatestring", "callee": "toISOString", "source_file": "C:\\Users\\pujar\\Documents\\TripSense(WAD)\\app\\api\\trips\\from-discover\\route.ts", "source_location": "L95"}, {"caller_nid": "route_adddays", "callee": "setUTCDate", "source_file": "C:\\Users\\pujar\\Documents\\TripSense(WAD)\\app\\api\\trips\\from-discover\\route.ts", "source_location": "L100"}, {"caller_nid": "route_adddays", "callee": "getUTCDate", "source_file": "C:\\Users\\pujar\\Documents\\TripSense(WAD)\\app\\api\\trips\\from-discover\\route.ts", "source_location": "L100"}, {"caller_nid": "route_adddays", "callee": "split", "source_file": "C:\\Users\\pujar\\Documents\\TripSense(WAD)\\app\\api\\trips\\from-discover\\route.ts", "source_location": "L101"}, {"caller_nid": "route_adddays", "callee": "toISOString", "source_file": "C:\\Users\\pujar\\Documents\\TripSense(WAD)\\app\\api\\trips\\from-discover\\route.ts", "source_location": "L101"}, {"caller_nid": "route_isvaliddatestring", "callee": "test", "source_file": "C:\\Users\\pujar\\Documents\\TripSense(WAD)\\app\\api\\trips\\from-discover\\route.ts", "source_location": "L105"}, {"caller_nid": "route_safestringarray", "callee": "isArray", "source_file": "C:\\Users\\pujar\\Documents\\TripSense(WAD)\\app\\api\\trips\\from-discover\\route.ts", "source_location": "L109"}, {"caller_nid": "route_safestringarray", "callee": "filter", "source_file": "C:\\Users\\pujar\\Documents\\TripSense(WAD)\\app\\api\\trips\\from-discover\\route.ts", "source_location": "L110"}, {"caller_nid": "route_safestringarray", "callee": "map", "source_file": "C:\\Users\\pujar\\Documents\\TripSense(WAD)\\app\\api\\trips\\from-discover\\route.ts", "source_location": "L110"}, {"caller_nid": "route_parsestatusfrommessage", "callee": "match", "source_file": "C:\\Users\\pujar\\Documents\\TripSense(WAD)\\app\\api\\trips\\from-discover\\route.ts", "source_location": "L114"}, {"caller_nid": "route_parsestatusfrommessage", "callee": "match", "source_file": "C:\\Users\\pujar\\Documents\\TripSense(WAD)\\app\\api\\trips\\from-discover\\route.ts", "source_location": "L114"}, {"caller_nid": "route_parsestatusfrommessage", "callee": "Number", "source_file": "C:\\Users\\pujar\\Documents\\TripSense(WAD)\\app\\api\\trips\\from-discover\\route.ts", "source_location": "L115"}, {"caller_nid": "route_istransientailoaderror", "callee": "toLowerCase", "source_file": "C:\\Users\\pujar\\Documents\\TripSense(WAD)\\app\\api\\trips\\from-discover\\route.ts", "source_location": "L119"}, {"caller_nid": "route_istransientailoaderror", "callee": "includes", "source_file": "C:\\Users\\pujar\\Documents\\TripSense(WAD)\\app\\api\\trips\\from-discover\\route.ts", "source_location": "L122"}, {"caller_nid": "route_istransientailoaderror", "callee": "includes", "source_file": "C:\\Users\\pujar\\Documents\\TripSense(WAD)\\app\\api\\trips\\from-discover\\route.ts", "source_location": "L127"}, {"caller_nid": "route_istransientailoaderror", "callee": "includes", "source_file": "C:\\Users\\pujar\\Documents\\TripSense(WAD)\\app\\api\\trips\\from-discover\\route.ts", "source_location": "L128"}, {"caller_nid": "route_istransientailoaderror", "callee": "includes", "source_file": "C:\\Users\\pujar\\Documents\\TripSense(WAD)\\app\\api\\trips\\from-discover\\route.ts", "source_location": "L129"}, {"caller_nid": "route_istransientailoaderror", "callee": "includes", "source_file": "C:\\Users\\pujar\\Documents\\TripSense(WAD)\\app\\api\\trips\\from-discover\\route.ts", "source_location": "L130"}, {"caller_nid": "route_parsedurationdays", "callee": "match", "source_file": "C:\\Users\\pujar\\Documents\\TripSense(WAD)\\app\\api\\trips\\from-discover\\route.ts", "source_location": "L135"}, {"caller_nid": "route_parsedurationdays", "callee": "String", "source_file": "C:\\Users\\pujar\\Documents\\TripSense(WAD)\\app\\api\\trips\\from-discover\\route.ts", "source_location": "L135"}, {"caller_nid": "route_parsedurationdays", "callee": "Number", "source_file": "C:\\Users\\pujar\\Documents\\TripSense(WAD)\\app\\api\\trips\\from-discover\\route.ts", "source_location": "L136"}, {"caller_nid": "route_parsedurationdays", "callee": "isInteger", "source_file": "C:\\Users\\pujar\\Documents\\TripSense(WAD)\\app\\api\\trips\\from-discover\\route.ts", "source_location": "L137"}, {"caller_nid": "route_infervibes", "callee": "from", "source_file": "C:\\Users\\pujar\\Documents\\TripSense(WAD)\\app\\api\\trips\\from-discover\\route.ts", "source_location": "L158"}, {"caller_nid": "route_infervibes", "callee": "filter", "source_file": "C:\\Users\\pujar\\Documents\\TripSense(WAD)\\app\\api\\trips\\from-discover\\route.ts", "source_location": "L161"}, {"caller_nid": "route_infervibes", "callee": "map", "source_file": "C:\\Users\\pujar\\Documents\\TripSense(WAD)\\app\\api\\trips\\from-discover\\route.ts", "source_location": "L161"}, {"caller_nid": "route_infervibes", "callee": "split", "source_file": "C:\\Users\\pujar\\Documents\\TripSense(WAD)\\app\\api\\trips\\from-discover\\route.ts", "source_location": "L161"}, {"caller_nid": "route_infervibes", "callee": "String", "source_file": "C:\\Users\\pujar\\Documents\\TripSense(WAD)\\app\\api\\trips\\from-discover\\route.ts", "source_location": "L161"}, {"caller_nid": "route_infervibes", "callee": "from", "source_file": "C:\\Users\\pujar\\Documents\\TripSense(WAD)\\app\\api\\trips\\from-discover\\route.ts", "source_location": "L166"}, {"caller_nid": "route_normalizesentence", "callee": "trim", "source_file": "C:\\Users\\pujar\\Documents\\TripSense(WAD)\\app\\api\\trips\\from-discover\\route.ts", "source_location": "L170"}, {"caller_nid": "route_normalizesentence", "callee": "replace", "source_file": "C:\\Users\\pujar\\Documents\\TripSense(WAD)\\app\\api\\trips\\from-discover\\route.ts", "source_location": "L170"}, {"caller_nid": "route_normalizesentence", "callee": "String", "source_file": "C:\\Users\\pujar\\Documents\\TripSense(WAD)\\app\\api\\trips\\from-discover\\route.ts", "source_location": "L170"}, {"caller_nid": "route_splitdescriptionintosegments", "callee": "filter", "source_file": "C:\\Users\\pujar\\Documents\\TripSense(WAD)\\app\\api\\trips\\from-discover\\route.ts", "source_location": "L176"}, {"caller_nid": "route_splitdescriptionintosegments", "callee": "map", "source_file": "C:\\Users\\pujar\\Documents\\TripSense(WAD)\\app\\api\\trips\\from-discover\\route.ts", "source_location": "L176"}, {"caller_nid": "route_splitdescriptionintosegments", "callee": "split", "source_file": "C:\\Users\\pujar\\Documents\\TripSense(WAD)\\app\\api\\trips\\from-discover\\route.ts", "source_location": "L176"}, {"caller_nid": "route_splitdescriptionintosegments", "callee": "slice", "source_file": "C:\\Users\\pujar\\Documents\\TripSense(WAD)\\app\\api\\trips\\from-discover\\route.ts", "source_location": "L182"}, {"caller_nid": "route_splitdescriptionintosegments", "callee": "filter", "source_file": "C:\\Users\\pujar\\Documents\\TripSense(WAD)\\app\\api\\trips\\from-discover\\route.ts", "source_location": "L185"}, {"caller_nid": "route_splitdescriptionintosegments", "callee": "map", "source_file": "C:\\Users\\pujar\\Documents\\TripSense(WAD)\\app\\api\\trips\\from-discover\\route.ts", "source_location": "L185"}, {"caller_nid": "route_splitdescriptionintosegments", "callee": "split", "source_file": "C:\\Users\\pujar\\Documents\\TripSense(WAD)\\app\\api\\trips\\from-discover\\route.ts", "source_location": "L185"}, {"caller_nid": "route_splitdescriptionintosegments", "callee": "slice", "source_file": "C:\\Users\\pujar\\Documents\\TripSense(WAD)\\app\\api\\trips\\from-discover\\route.ts", "source_location": "L191"}, {"caller_nid": "route_inferactivitytype", "callee": "toLowerCase", "source_file": "C:\\Users\\pujar\\Documents\\TripSense(WAD)\\app\\api\\trips\\from-discover\\route.ts", "source_location": "L198"}, {"caller_nid": "route_inferactivitytype", "callee": "test", "source_file": "C:\\Users\\pujar\\Documents\\TripSense(WAD)\\app\\api\\trips\\from-discover\\route.ts", "source_location": "L201"}, {"caller_nid": "route_inferactivitytype", "callee": "test", "source_file": "C:\\Users\\pujar\\Documents\\TripSense(WAD)\\app\\api\\trips\\from-discover\\route.ts", "source_location": "L209"}, {"caller_nid": "route_extractproperphrases", "callee": "match", "source_file": "C:\\Users\\pujar\\Documents\\TripSense(WAD)\\app\\api\\trips\\from-discover\\route.ts", "source_location": "L221"}, {"caller_nid": "route_extractproperphrases", "callee": "filter", "source_file": "C:\\Users\\pujar\\Documents\\TripSense(WAD)\\app\\api\\trips\\from-discover\\route.ts", "source_location": "L223"}, {"caller_nid": "route_extractproperphrases", "callee": "map", "source_file": "C:\\Users\\pujar\\Documents\\TripSense(WAD)\\app\\api\\trips\\from-discover\\route.ts", "source_location": "L223"}, {"caller_nid": "route_extractproperphrases", "callee": "from", "source_file": "C:\\Users\\pujar\\Documents\\TripSense(WAD)\\app\\api\\trips\\from-discover\\route.ts", "source_location": "L230"}, {"caller_nid": "route_sentencetoactivitytitle", "callee": "trim", "source_file": "C:\\Users\\pujar\\Documents\\TripSense(WAD)\\app\\api\\trips\\from-discover\\route.ts", "source_location": "L247"}, {"caller_nid": "route_sentencetoactivitytitle", "callee": "replace", "source_file": "C:\\Users\\pujar\\Documents\\TripSense(WAD)\\app\\api\\trips\\from-discover\\route.ts", "source_location": "L247"}, {"caller_nid": "route_sentencetoactivitytitle", "callee": "replace", "source_file": "C:\\Users\\pujar\\Documents\\TripSense(WAD)\\app\\api\\trips\\from-discover\\route.ts", "source_location": "L247"}, {"caller_nid": "route_sentencetoactivitytitle", "callee": "join", "source_file": "C:\\Users\\pujar\\Documents\\TripSense(WAD)\\app\\api\\trips\\from-discover\\route.ts", "source_location": "L259"}, {"caller_nid": "route_sentencetoactivitytitle", "callee": "slice", "source_file": "C:\\Users\\pujar\\Documents\\TripSense(WAD)\\app\\api\\trips\\from-discover\\route.ts", "source_location": "L259"}, {"caller_nid": "route_sentencetoactivitytitle", "callee": "split", "source_file": "C:\\Users\\pujar\\Documents\\TripSense(WAD)\\app\\api\\trips\\from-discover\\route.ts", "source_location": "L259"}, {"caller_nid": "route_sentencetoactivitytitle", "callee": "toUpperCase", "source_file": "C:\\Users\\pujar\\Documents\\TripSense(WAD)\\app\\api\\trips\\from-discover\\route.ts", "source_location": "L260"}, {"caller_nid": "route_sentencetoactivitytitle", "callee": "charAt", "source_file": "C:\\Users\\pujar\\Documents\\TripSense(WAD)\\app\\api\\trips\\from-discover\\route.ts", "source_location": "L260"}, {"caller_nid": "route_sentencetoactivitytitle", "callee": "slice", "source_file": "C:\\Users\\pujar\\Documents\\TripSense(WAD)\\app\\api\\trips\\from-discover\\route.ts", "source_location": "L260"}, {"caller_nid": "route_buildseededfallbackimage", "callee": "encodeURIComponent", "source_file": "C:\\Users\\pujar\\Documents\\TripSense(WAD)\\app\\api\\trips\\from-discover\\route.ts", "source_location": "L264"}, {"caller_nid": "route_inferbridgeactivitytitle", "callee": "filter", "source_file": "C:\\Users\\pujar\\Documents\\TripSense(WAD)\\app\\api\\trips\\from-discover\\route.ts", "source_location": "L270"}, {"caller_nid": "route_buildfallbackactivitiesforday", "callee": "trim", "source_file": "C:\\Users\\pujar\\Documents\\TripSense(WAD)\\app\\api\\trips\\from-discover\\route.ts", "source_location": "L294"}, {"caller_nid": "route_buildfallbackactivitiesforday", "callee": "split", "source_file": "C:\\Users\\pujar\\Documents\\TripSense(WAD)\\app\\api\\trips\\from-discover\\route.ts", "source_location": "L294"}, {"caller_nid": "route_buildfallbackactivitiesforday", "callee": "endsWith", "source_file": "C:\\Users\\pujar\\Documents\\TripSense(WAD)\\app\\api\\trips\\from-discover\\route.ts", "source_location": "L296"}, {"caller_nid": "route_mergeactivitieswithfallback", "callee": "map", "source_file": "C:\\Users\\pujar\\Documents\\TripSense(WAD)\\app\\api\\trips\\from-discover\\route.ts", "source_location": "L411"}, {"caller_nid": "route_mergeactivitieswithfallback", "callee": "toLowerCase", "source_file": "C:\\Users\\pujar\\Documents\\TripSense(WAD)\\app\\api\\trips\\from-discover\\route.ts", "source_location": "L419"}, {"caller_nid": "route_mergeactivitieswithfallback", "callee": "has", "source_file": "C:\\Users\\pujar\\Documents\\TripSense(WAD)\\app\\api\\trips\\from-discover\\route.ts", "source_location": "L420"}, {"caller_nid": "route_mergeactivitieswithfallback", "callee": "push", "source_file": "C:\\Users\\pujar\\Documents\\TripSense(WAD)\\app\\api\\trips\\from-discover\\route.ts", "source_location": "L422"}, {"caller_nid": "route_mergeactivitieswithfallback", "callee": "add", "source_file": "C:\\Users\\pujar\\Documents\\TripSense(WAD)\\app\\api\\trips\\from-discover\\route.ts", "source_location": "L423"}, {"caller_nid": "route_mergeactivitieswithfallback", "callee": "slice", "source_file": "C:\\Users\\pujar\\Documents\\TripSense(WAD)\\app\\api\\trips\\from-discover\\route.ts", "source_location": "L426"}, {"caller_nid": "route_mergeactivitieswithfallback", "callee": "sort", "source_file": "C:\\Users\\pujar\\Documents\\TripSense(WAD)\\app\\api\\trips\\from-discover\\route.ts", "source_location": "L426"}, {"caller_nid": "route_sanitizegenerateddiscoveritinerary", "callee": "map", "source_file": "C:\\Users\\pujar\\Documents\\TripSense(WAD)\\app\\api\\trips\\from-discover\\route.ts", "source_location": "L440"}, {"caller_nid": "route_sanitizegenerateddiscoveritinerary", "callee": "isArray", "source_file": "C:\\Users\\pujar\\Documents\\TripSense(WAD)\\app\\api\\trips\\from-discover\\route.ts", "source_location": "L448"}, {"caller_nid": "route_sanitizegenerateddiscoveritinerary", "callee": "map", "source_file": "C:\\Users\\pujar\\Documents\\TripSense(WAD)\\app\\api\\trips\\from-discover\\route.ts", "source_location": "L449"}, {"caller_nid": "route_sanitizegenerateddiscoveritinerary", "callee": "map", "source_file": "C:\\Users\\pujar\\Documents\\TripSense(WAD)\\app\\api\\trips\\from-discover\\route.ts", "source_location": "L456"}, {"caller_nid": "route_builddiscoverexpansionprompt", "callee": "stringify", "source_file": "C:\\Users\\pujar\\Documents\\TripSense(WAD)\\app\\api\\trips\\from-discover\\route.ts", "source_location": "L562"}, {"caller_nid": "route_resolveuserid", "callee": "toLowerCase", "source_file": "C:\\Users\\pujar\\Documents\\TripSense(WAD)\\app\\api\\trips\\from-discover\\route.ts", "source_location": "L580"}, {"caller_nid": "route_resolveuserid", "callee": "trim", "source_file": "C:\\Users\\pujar\\Documents\\TripSense(WAD)\\app\\api\\trips\\from-discover\\route.ts", "source_location": "L580"}, {"caller_nid": "route_resolveuserid", "callee": "String", "source_file": "C:\\Users\\pujar\\Documents\\TripSense(WAD)\\app\\api\\trips\\from-discover\\route.ts", "source_location": "L580"}, {"caller_nid": "route_resolveuserid", "callee": "limit", "source_file": "C:\\Users\\pujar\\Documents\\TripSense(WAD)\\app\\api\\trips\\from-discover\\route.ts", "source_location": "L585"}, {"caller_nid": "route_resolveuserid", "callee": "where", "source_file": "C:\\Users\\pujar\\Documents\\TripSense(WAD)\\app\\api\\trips\\from-discover\\route.ts", "source_location": "L585"}, {"caller_nid": "route_resolveuserid", "callee": "from", "source_file": "C:\\Users\\pujar\\Documents\\TripSense(WAD)\\app\\api\\trips\\from-discover\\route.ts", "source_location": "L585"}, {"caller_nid": "route_resolveuserid", "callee": "select", "source_file": "C:\\Users\\pujar\\Documents\\TripSense(WAD)\\app\\api\\trips\\from-discover\\route.ts", "source_location": "L585"}, {"caller_nid": "route_resolveuserid", "callee": "eq", "source_file": "C:\\Users\\pujar\\Documents\\TripSense(WAD)\\app\\api\\trips\\from-discover\\route.ts", "source_location": "L588"}, {"caller_nid": "route_resolveuserid", "callee": "returning", "source_file": "C:\\Users\\pujar\\Documents\\TripSense(WAD)\\app\\api\\trips\\from-discover\\route.ts", "source_location": "L595"}, {"caller_nid": "route_resolveuserid", "callee": "values", "source_file": "C:\\Users\\pujar\\Documents\\TripSense(WAD)\\app\\api\\trips\\from-discover\\route.ts", "source_location": "L595"}, {"caller_nid": "route_resolveuserid", "callee": "insert", "source_file": "C:\\Users\\pujar\\Documents\\TripSense(WAD)\\app\\api\\trips\\from-discover\\route.ts", "source_location": "L595"}, {"caller_nid": "route_buildestimateprompt", "callee": "stringify", "source_file": "C:\\Users\\pujar\\Documents\\TripSense(WAD)\\app\\api\\trips\\from-discover\\route.ts", "source_location": "L633"}, {"caller_nid": "route_post", "callee": "json", "source_file": "C:\\Users\\pujar\\Documents\\TripSense(WAD)\\app\\api\\trips\\from-discover\\route.ts", "source_location": "L652"}, {"caller_nid": "route_post", "callee": "trim", "source_file": "C:\\Users\\pujar\\Documents\\TripSense(WAD)\\app\\api\\trips\\from-discover\\route.ts", "source_location": "L653"}, {"caller_nid": "route_post", "callee": "String", "source_file": "C:\\Users\\pujar\\Documents\\TripSense(WAD)\\app\\api\\trips\\from-discover\\route.ts", "source_location": "L653"}, {"caller_nid": "route_post", "callee": "json", "source_file": "C:\\Users\\pujar\\Documents\\TripSense(WAD)\\app\\api\\trips\\from-discover\\route.ts", "source_location": "L656"}, {"caller_nid": "route_post", "callee": "getDiscoverTripBySlug", "source_file": "C:\\Users\\pujar\\Documents\\TripSense(WAD)\\app\\api\\trips\\from-discover\\route.ts", "source_location": "L659"}, {"caller_nid": "route_post", "callee": "json", "source_file": "C:\\Users\\pujar\\Documents\\TripSense(WAD)\\app\\api\\trips\\from-discover\\route.ts", "source_location": "L661"}, {"caller_nid": "route_post", "callee": "trim", "source_file": "C:\\Users\\pujar\\Documents\\TripSense(WAD)\\app\\api\\trips\\from-discover\\route.ts", "source_location": "L664"}, {"caller_nid": "route_post", "callee": "String", "source_file": "C:\\Users\\pujar\\Documents\\TripSense(WAD)\\app\\api\\trips\\from-discover\\route.ts", "source_location": "L664"}, {"caller_nid": "route_post", "callee": "trim", "source_file": "C:\\Users\\pujar\\Documents\\TripSense(WAD)\\app\\api\\trips\\from-discover\\route.ts", "source_location": "L665"}, {"caller_nid": "route_post", "callee": "String", "source_file": "C:\\Users\\pujar\\Documents\\TripSense(WAD)\\app\\api\\trips\\from-discover\\route.ts", "source_location": "L665"}, {"caller_nid": "route_post", "callee": "String", "source_file": "C:\\Users\\pujar\\Documents\\TripSense(WAD)\\app\\api\\trips\\from-discover\\route.ts", "source_location": "L669"}, {"caller_nid": "route_post", "callee": "trim", "source_file": "C:\\Users\\pujar\\Documents\\TripSense(WAD)\\app\\api\\trips\\from-discover\\route.ts", "source_location": "L670"}, {"caller_nid": "route_post", "callee": "String", "source_file": "C:\\Users\\pujar\\Documents\\TripSense(WAD)\\app\\api\\trips\\from-discover\\route.ts", "source_location": "L670"}, {"caller_nid": "route_post", "callee": "trim", "source_file": "C:\\Users\\pujar\\Documents\\TripSense(WAD)\\app\\api\\trips\\from-discover\\route.ts", "source_location": "L672"}, {"caller_nid": "route_post", "callee": "String", "source_file": "C:\\Users\\pujar\\Documents\\TripSense(WAD)\\app\\api\\trips\\from-discover\\route.ts", "source_location": "L672"}, {"caller_nid": "route_post", "callee": "String", "source_file": "C:\\Users\\pujar\\Documents\\TripSense(WAD)\\app\\api\\trips\\from-discover\\route.ts", "source_location": "L673"}, {"caller_nid": "route_post", "callee": "await generateStructuredJson", "source_file": "C:\\Users\\pujar\\Documents\\TripSense(WAD)\\app\\api\\trips\\from-discover\\route.ts", "source_location": "L677"}, {"caller_nid": "route_post", "callee": "await generateStructuredJson", "source_file": "C:\\Users\\pujar\\Documents\\TripSense(WAD)\\app\\api\\trips\\from-discover\\route.ts", "source_location": "L713"}, {"caller_nid": "route_post", "callee": "normalizeEstimatedCostForDb", "source_file": "C:\\Users\\pujar\\Documents\\TripSense(WAD)\\app\\api\\trips\\from-discover\\route.ts", "source_location": "L730"}, {"caller_nid": "route_post", "callee": "normalizeEstimatedCurrency", "source_file": "C:\\Users\\pujar\\Documents\\TripSense(WAD)\\app\\api\\trips\\from-discover\\route.ts", "source_location": "L731"}, {"caller_nid": "route_post", "callee": "normalizeEstimateNote", "source_file": "C:\\Users\\pujar\\Documents\\TripSense(WAD)\\app\\api\\trips\\from-discover\\route.ts", "source_location": "L732"}, {"caller_nid": "route_post", "callee": "returning", "source_file": "C:\\Users\\pujar\\Documents\\TripSense(WAD)\\app\\api\\trips\\from-discover\\route.ts", "source_location": "L737"}, {"caller_nid": "route_post", "callee": "values", "source_file": "C:\\Users\\pujar\\Documents\\TripSense(WAD)\\app\\api\\trips\\from-discover\\route.ts", "source_location": "L737"}, {"caller_nid": "route_post", "callee": "insert", "source_file": "C:\\Users\\pujar\\Documents\\TripSense(WAD)\\app\\api\\trips\\from-discover\\route.ts", "source_location": "L737"}, {"caller_nid": "route_post", "callee": "entries", "source_file": "C:\\Users\\pujar\\Documents\\TripSense(WAD)\\app\\api\\trips\\from-discover\\route.ts", "source_location": "L758"}, {"caller_nid": "route_post", "callee": "returning", "source_file": "C:\\Users\\pujar\\Documents\\TripSense(WAD)\\app\\api\\trips\\from-discover\\route.ts", "source_location": "L759"}, {"caller_nid": "route_post", "callee": "values", "source_file": "C:\\Users\\pujar\\Documents\\TripSense(WAD)\\app\\api\\trips\\from-discover\\route.ts", "source_location": "L759"}, {"caller_nid": "route_post", "callee": "insert", "source_file": "C:\\Users\\pujar\\Documents\\TripSense(WAD)\\app\\api\\trips\\from-discover\\route.ts", "source_location": "L759"}, {"caller_nid": "route_post", "callee": "all", "source_file": "C:\\Users\\pujar\\Documents\\TripSense(WAD)\\app\\api\\trips\\from-discover\\route.ts", "source_location": "L768"}, {"caller_nid": "route_post", "callee": "map", "source_file": "C:\\Users\\pujar\\Documents\\TripSense(WAD)\\app\\api\\trips\\from-discover\\route.ts", "source_location": "L769"}, {"caller_nid": "route_post", "callee": "values", "source_file": "C:\\Users\\pujar\\Documents\\TripSense(WAD)\\app\\api\\trips\\from-discover\\route.ts", "source_location": "L817"}, {"caller_nid": "route_post", "callee": "insert", "source_file": "C:\\Users\\pujar\\Documents\\TripSense(WAD)\\app\\api\\trips\\from-discover\\route.ts", "source_location": "L817"}, {"caller_nid": "route_post", "callee": "json", "source_file": "C:\\Users\\pujar\\Documents\\TripSense(WAD)\\app\\api\\trips\\from-discover\\route.ts", "source_location": "L821"}, {"caller_nid": "route_post", "callee": "json", "source_file": "C:\\Users\\pujar\\Documents\\TripSense(WAD)\\app\\api\\trips\\from-discover\\route.ts", "source_location": "L826"}]}